lingkar33423308/__init__.py
lingkar33423308/lingkar.py
lingkar33423308-1.1.dist-info/LICENSE
lingkar33423308-1.1.dist-info/METADATA
lingkar33423308-1.1.dist-info/WHEEL
lingkar33423308-1.1.dist-info/top_level.txt
lingkar33423308-1.1.dist-info/RECORD
