Metadata-Version: 2.1
Name: lingkar33423308
Version: 1.1
Summary: Menghitung luas lingkaran
Author: Aliza
Author-email: <faizata00@gmail.com>
License: MIT
Keywords: luas,lingkaran
Classifier: Development Status :: 1 - Planning
License-File: LICENSE
